polytomic/__init__.py
polytomic/bulk_sync/__init__.py
polytomic/bulk_sync/client.py
polytomic/bulk_sync/executions/__init__.py
polytomic/bulk_sync/executions/client.py
polytomic/bulk_sync/schemas/__init__.py
polytomic/bulk_sync/schemas/client.py
polytomic/bulk_sync/types/__init__.py
polytomic/bulk_sync/types/v_2_create_bulk_sync_request_schemas_item.py
polytomic/bulk_sync/types/v_2_update_bulk_sync_request_schemas_item.py
polytomic/client.py
polytomic/connections/__init__.py
polytomic/connections/client.py
polytomic/core/__init__.py
polytomic/core/api_error.py
polytomic/core/client_wrapper.py
polytomic/core/datetime_utils.py
polytomic/core/file.py
polytomic/core/http_client.py
polytomic/core/jsonable_encoder.py
polytomic/core/pydantic_utilities.py
polytomic/core/query_encoder.py
polytomic/core/remove_none_from_dict.py
polytomic/core/request_options.py
polytomic/core/serialization.py
polytomic/environment.py
polytomic/errors/__init__.py
polytomic/errors/bad_request_error.py
polytomic/errors/conflict_error.py
polytomic/errors/forbidden_error.py
polytomic/errors/internal_server_error.py
polytomic/errors/not_found_error.py
polytomic/errors/unauthorized_error.py
polytomic/errors/unprocessable_entity_error.py
polytomic/events/__init__.py
polytomic/events/client.py
polytomic/identity/__init__.py
polytomic/identity/client.py
polytomic/jobs/__init__.py
polytomic/jobs/client.py
polytomic/model_sync/__init__.py
polytomic/model_sync/client.py
polytomic/model_sync/executions/__init__.py
polytomic/model_sync/executions/client.py
polytomic/models/__init__.py
polytomic/models/client.py
polytomic/organization/__init__.py
polytomic/organization/client.py
polytomic/permissions/__init__.py
polytomic/permissions/client.py
polytomic/permissions/policies/__init__.py
polytomic/permissions/policies/client.py
polytomic/permissions/roles/__init__.py
polytomic/permissions/roles/client.py
polytomic/py.typed
polytomic/query_runner/__init__.py
polytomic/query_runner/client.py
polytomic-1.11.3.dist-info/LICENSE
polytomic-1.11.3.dist-info/METADATA
polytomic-1.11.3.dist-info/WHEEL
polytomic-1.11.3.dist-info/RECORD
